exceptionx/__init__.py
exceptionx/i exceptionx.py
exceptionx-4.1.8.dist-info/LICENSE
exceptionx-4.1.8.dist-info/METADATA
exceptionx-4.1.8.dist-info/WHEEL
exceptionx-4.1.8.dist-info/top_level.txt
exceptionx-4.1.8.dist-info/RECORD
