Metadata-Version: 2.1
Name: exceptionx
Version: 4.1.8
Summary: The `exceptionx` is a flexible and convenient Python exception handling library that allows you to dynamically create exception classes and provides various exception handling mechanisms.
Home-page: http://gqylpy.com
Author: Unnamed great master
Author-email: <gqylpy@outlook.com>
License: MIT
Project-URL: Source, https://github.com/gqylpy/exceptionx
Classifier: Development Status :: 4 - Beta
Classifier: Intended Audience :: Developers
Classifier: License :: OSI Approved :: MIT License
Classifier: Natural Language :: Chinese (Simplified)
Classifier: Natural Language :: English
Classifier: Operating System :: OS Independent
Classifier: Topic :: Software Development :: Libraries :: Python Modules
Classifier: Topic :: Software Development :: Bug Tracking
Classifier: Topic :: Software Development :: Widget Sets
Classifier: Topic :: Artistic Software
Classifier: Programming Language :: Python :: 3.8
Classifier: Programming Language :: Python :: 3.9
Classifier: Programming Language :: Python :: 3.10
Classifier: Programming Language :: Python :: 3.11
Classifier: Programming Language :: Python :: 3.12
Classifier: Programming Language :: Python :: 3.13
Requires-Python: >=3.8
License-File: LICENSE
